AUTHORS
LICENSE
MANIFEST.in
README.rst
flask_beaker.py
setup.py
Flask_Beaker.egg-info/PKG-INFO
Flask_Beaker.egg-info/SOURCES.txt
Flask_Beaker.egg-info/dependency_links.txt
Flask_Beaker.egg-info/not-zip-safe
Flask_Beaker.egg-info/requires.txt
Flask_Beaker.egg-info/top_level.txt